requesturl/__init__.py
requesturl/cli.py
requesturl/request_url.py
requesturl-0.2.4.dist-info/AUTHORS.rst
requesturl-0.2.4.dist-info/METADATA
requesturl-0.2.4.dist-info/WHEEL
requesturl-0.2.4.dist-info/entry_points.txt
requesturl-0.2.4.dist-info/top_level.txt
requesturl-0.2.4.dist-info/RECORD
