Metadata-Version: 2.1
Name: requesturl
Version: 0.2.4
Summary: Request URL
Home-page: https://github.com/yasirerkam/requesturl
Author: Yasir Erkam Özdemir
Author-email: yasir.erkam17@gmail.com
License: Attribution-ShareAlike 4.0 International (CC BY-SA 4.0)
Keywords: requesturl
Platform: UNKNOWN
Classifier: Development Status :: 2 - Pre-Alpha
Classifier: Intended Audience :: Developers
Classifier: Natural Language :: English
Classifier: Programming Language :: Python :: 3
Classifier: Programming Language :: Python :: 3.6
Classifier: Programming Language :: Python :: 3.7
Classifier: Programming Language :: Python :: 3.8
Classifier: Programming Language :: Python :: 3.9
Requires-Python: >=3.6
Requires-Dist: Click (>=7.0)
Requires-Dist: free-proxy (==1.0.2)
Requires-Dist: Proxy-List-Scrapper (==0.2.2)
